{"pageContext":{"slug":"/warn-sap-users-of-locked-objects-then-kill-their-session/","prev":{"fields":{"slug":"/welp-i-did-it-i-quit/"},"frontmatter":{"date":"22 July, 2018","title":"Welp, I Did It. I Quit.","draft":false,"link":"https://chrisfrew.in/welp-i-did-it-i-quit/","relativeLink":"/welp-i-did-it-i-quit/"}},"next":{"fields":{"slug":"/the-social-contract/"},"frontmatter":{"date":"28 October, 2018","title":"The Software Engineer's Social Contract","draft":false,"link":"https://chrisfrew.in/the-social-contract/","relativeLink":"/the-social-contract/"}}}}